lcz/__init__.py
lcz/backends.py
lcz/main.py
lcz/uci.py
lcz/weights/__init__.py
lcz/weights/maia-1900.pb.gz
lcz/weights/weights.py
lcz-0.1.7.dist-info/METADATA
lcz-0.1.7.dist-info/WHEEL
lcz-0.1.7.dist-info/top_level.txt
lcz-0.1.7.dist-info/RECORD
