Metadata-Version: 2.1
Name: lcz
Version: 0.1.7
Summary: Simplified Leela Chess Zero (aka lc0 aka lcz) with Python
Author-email: Marcel Claramunt <marcel@moveread.com>
Project-URL: repo, https://github.com/moveread/chess
Requires-Python: >=3.10
Requires-Dist: meson ==1.2.2
Requires-Dist: ninja
Requires-Dist: lczero-bindings
